config/ODataToSTAC_template.json
config/prip_search_config.template.yaml
config/prip_search_config.yaml
config/prip_stac_mapper.json
config/prip_ws_config.template.yaml
config/prip_ws_config.yaml
config/prip_ws_config_token_module.template.yaml
config/prip_ws_config_token_module.yaml
rs_server_prip/__init__.py
rs_server_prip/api/__init__.py
rs_server_prip/api/prip_search.py
rs_server_prip/fastapi/__init__.py
rs_server_prip/fastapi/prip_app.py
rs_server_prip/fastapi/prip_routers.py
rs_server_prip/prip_retriever.py
rs_server_prip/prip_utils.py
rs_server_prip-1.0a6.dist-info/METADATA
rs_server_prip-1.0a6.dist-info/WHEEL
rs_server_prip-1.0a6.dist-info/RECORD
