Metadata-Version: 2.4
Name: rs-server-prip
Version: 1.0a6
Summary: Copernicus Sentinel rs-server, PRIP service.
License: Apache-2.0
Keywords: stac,copernicus,sentinel,processing,prip
Author: ESA under contract with Airbus and CS
Author-email: ops_coprs@airbus.com
Requires-Python: >=3.13,<4
Classifier: Development Status :: 3 - Alpha
Classifier: Framework :: FastAPI
Classifier: Framework :: OpenTelemetry
Classifier: Intended Audience :: Developers
Classifier: Intended Audience :: Science/Research
Classifier: License :: OSI Approved :: Apache Software License
Classifier: Programming Language :: Python :: 3
Classifier: Programming Language :: Python :: 3.13
Classifier: Programming Language :: Python :: 3.14
Classifier: Topic :: Scientific/Engineering :: GIS
Classifier: Topic :: Scientific/Engineering :: Image Processing
Requires-Dist: rs-server-common
Project-URL: Documentation, https://home.rs-python.eu/rs-documentation/rs-server/docs/doc/users/functionalities/#prip
Project-URL: Homepage, https://home.rs-python.eu/
Project-URL: Repository, https://github.com/RS-PYTHON/rs-server
